odoo9_addon_medical_medicament_component-9.0.1.0.0-py2.7-nspkg.pth
odoo_addons/medical_medicament_component/__openerp__.py
odoo_addons/medical_medicament_component/__init__.py
odoo_addons/medical_medicament_component/README.rst
odoo_addons/medical_medicament_component/security/ir.model.access.csv
odoo_addons/medical_medicament_component/models/medical_medicament.py
odoo_addons/medical_medicament_component/models/medical_medicament_component.py
odoo_addons/medical_medicament_component/models/__init__.py
odoo_addons/medical_medicament_component/views/medical_medicament_component_view.xml
odoo_addons/medical_medicament_component/views/medical_menu.xml
odoo_addons/medical_medicament_component/views/medical_medicament_view.xml
odoo_addons/medical_medicament_component/tests/__init__.py
odoo_addons/medical_medicament_component/tests/test_medical_medicament_component.py
odoo_addons/medical_medicament_component/tests/medical_medicament_component.yml
odoo_addons/medical_medicament_component/static/description/icon.png
odoo9_addon_medical_medicament_component-9.0.1.0.0.dist-info/top_level.txt
odoo9_addon_medical_medicament_component-9.0.1.0.0.dist-info/WHEEL
odoo9_addon_medical_medicament_component-9.0.1.0.0.dist-info/RECORD
odoo9_addon_medical_medicament_component-9.0.1.0.0.dist-info/metadata.json
odoo9_addon_medical_medicament_component-9.0.1.0.0.dist-info/DESCRIPTION.rst
odoo9_addon_medical_medicament_component-9.0.1.0.0.dist-info/METADATA
odoo9_addon_medical_medicament_component-9.0.1.0.0.dist-info/namespace_packages.txt
